dramatist/TextBlock.py
dramatist/__init__.py
dramatist/cli/DramatistCLI.py
dramatist/cli/__init__.py
dramatist/core/Dramatist.py
dramatist/core/DramatistParseException.py
dramatist/core/__init__.py
dramatist/drama/Act.py
dramatist/drama/Drama.py
dramatist/drama/Markup.py
dramatist/drama/Scene.py
dramatist/drama/ScenePart.py
dramatist/drama/Speaker.py
dramatist/drama/Speech.py
dramatist/drama/SpeechPart.py
dramatist/drama/StageDirection.py
dramatist/drama/__init__.py
dramatist-0.1.0.dist-info/licenses/LICENSE
dramatist-0.1.0.dist-info/METADATA
dramatist-0.1.0.dist-info/WHEEL
dramatist-0.1.0.dist-info/entry_points.txt
dramatist-0.1.0.dist-info/top_level.txt
dramatist-0.1.0.dist-info/RECORD
