Metadata-Version: 2.4
Name: Dramatist
Version: 0.1.0
Summary: Dramatist is a project for parsing plays from DraCor (https://dracor.org/) into a data structure which allows to access the text of the play "character" perfect, that is, character start and end positions for various parts, for example, act or scenes, can be retrieved. This also allows for functionality like getting the act and scene number for a character position.
Author-email: Frederik Arnold <frederik.arnold@hu-berlin.de>
License:                                  Apache License
Project-URL: Homepage, https://hu.berlin/dramatist
Keywords: play,drama,nlp
Classifier: Programming Language :: Python :: 3
Classifier: License :: OSI Approved :: Apache Software License
Classifier: Operating System :: OS Independent
Requires-Python: >=3.11
License-File: LICENSE
Requires-Dist: requests>=2.32.0
Dynamic: license-file
